ZhichiXiangliangJiTongsuDaolunLijieSvmDeSancengJingjieLatexBan/README.md
ZhichiXiangliangJiTongsuDaolunLijieSvmDeSancengJingjieLatexBan/__init__.py
ZhichiXiangliangJiTongsuDaolunLijieSvmDeSancengJingjieLatexBan/__main__.py
ZhichiXiangliangJiTongsuDaolunLijieSvmDeSancengJingjieLatexBan/file.pdf
ZhichiXiangliangJiTongsuDaolunLijieSvmDeSancengJingjieLatexBan/index.html
zhichi_xiangliang_ji_tongsu_daolun_lijie_svm_de_sanceng_jingjie_latex_ban-2024.3.2.0.dist-info/METADATA
zhichi_xiangliang_ji_tongsu_daolun_lijie_svm_de_sanceng_jingjie_latex_ban-2024.3.2.0.dist-info/WHEEL
zhichi_xiangliang_ji_tongsu_daolun_lijie_svm_de_sanceng_jingjie_latex_ban-2024.3.2.0.dist-info/entry_points.txt
zhichi_xiangliang_ji_tongsu_daolun_lijie_svm_de_sanceng_jingjie_latex_ban-2024.3.2.0.dist-info/top_level.txt
zhichi_xiangliang_ji_tongsu_daolun_lijie_svm_de_sanceng_jingjie_latex_ban-2024.3.2.0.dist-info/RECORD
